robotframework_practitest/__init__.py
robotframework_practitest/listener.py
robotframework_practitest/version.py
robotframework_practitest/models/__init__.py
robotframework_practitest/models/adapter.py
robotframework_practitest/models/field_adapter.py
robotframework_practitest/models/practi_test/__init__.py
robotframework_practitest/models/practi_test/client.py
robotframework_practitest/models/practi_test/data_formatters.py
robotframework_practitest/models/robot/__init__.py
robotframework_practitest/models/robot/helpers.py
robotframework_practitest/models/robot/html_decoder.py
robotframework_practitest/models/robot/wrappers.py
robotframework_practitest/services/__init__.py
robotframework_practitest/services/configuration.py
robotframework_practitest/services/data_queue.py
robotframework_practitest/services/scheduler.py
robotframework_practitest/services/session_wrapper.py
robotframework_practitest/services/statistics.py
robotframework_practitest/utils/__init__.py
robotframework_practitest/utils/courtesy_generator.py
robotframework_practitest/utils/logger.py
robotframework_practitest/utils/misc_utils.py
robotframework_practitest/utils/singleton.py
robotframework_practitest/utils/thread_pool.py
robotframework_practitest-1.2.53.dist-info/LICENSE
robotframework_practitest-1.2.53.dist-info/METADATA
robotframework_practitest-1.2.53.dist-info/WHEEL
robotframework_practitest-1.2.53.dist-info/top_level.txt
robotframework_practitest-1.2.53.dist-info/RECORD
