Metadata-Version: 2.1
Name: robotframework-practitest
Version: 1.2.53
Summary: RobotFW plugin for report to PractiTest
Home-page: https://github.com/doguz2509/robotframework_practitest
Author: Dmitry Oguz
Author-email: doguz2509@gmail.com
License: MIT
Classifier: Programming Language :: Python :: 3
Classifier: Framework :: Robot Framework
Classifier: Framework :: Robot Framework :: Library
Classifier: Operating System :: OS Independent
Classifier: Development Status :: 3 - Alpha
License-File: LICENSE
Requires-Dist: PyYAML
Requires-Dist: requests
Requires-Dist: pandas
Requires-Dist: robotframework
Requires-Dist: robotframework-datadriver
Requires-Dist: urllib3
